winrm/__init__.py
winrm/encryption.py
winrm/exceptions.py
winrm/protocol.py
winrm/py.typed
winrm/transport.py
winrm/tests/__init__.py
winrm/tests/conftest.py
winrm/tests/sample_script.ps1
winrm/tests/test_cmd.py
winrm/tests/test_encryption.py
winrm/tests/test_exceptions.py
winrm/tests/test_integration_protocol.py
winrm/tests/test_integration_session.py
winrm/tests/test_nori_type_casting.py
winrm/tests/test_powershell.py
winrm/tests/test_protocol.py
winrm/tests/test_session.py
winrm/tests/test_transport.py
winrm/tests/test_wql.py
winrm/vendor/__init__.py
winrm/vendor/requests_kerberos/__init__.py
winrm/vendor/requests_kerberos/compat.py
winrm/vendor/requests_kerberos/exceptions.py
winrm/vendor/requests_kerberos/kerberos_.py
pywinrm-0.5.0.dist-info/LICENSE
pywinrm-0.5.0.dist-info/METADATA
pywinrm-0.5.0.dist-info/WHEEL
pywinrm-0.5.0.dist-info/top_level.txt
pywinrm-0.5.0.dist-info/RECORD
