Metadata-Version: 2.1
Name: pywinrm
Version: 0.5.0
Summary: Python library for Windows Remote Management
Author-email: Alexey Diyan <alexey.diyan@gmail.com>
License: Copyright (c) 2013 Alexey Diyan
Project-URL: homepage, http://github.com/diyan/pywinrm/
Keywords: winrm,ws-man,devops,ws-management
Classifier: Development Status :: 4 - Beta
Classifier: Environment :: Console
Classifier: Intended Audience :: Developers
Classifier: Intended Audience :: System Administrators
Classifier: Natural Language :: English
Classifier: License :: OSI Approved :: MIT License
Classifier: Programming Language :: Python
Classifier: Programming Language :: Python :: 3
Classifier: Programming Language :: Python :: 3.8
Classifier: Programming Language :: Python :: 3.9
Classifier: Programming Language :: Python :: 3.10
Classifier: Programming Language :: Python :: 3.11
Classifier: Programming Language :: Python :: 3.12
Classifier: Programming Language :: Python :: Implementation :: PyPy
Classifier: Topic :: Software Development :: Libraries :: Python Modules
Classifier: Topic :: System :: Clustering
Classifier: Topic :: System :: Distributed Computing
Classifier: Topic :: System :: Systems Administration
Requires-Python: >=3.8
License-File: LICENSE
Requires-Dist: requests>=2.9.1
Requires-Dist: requests_ntlm>=1.1.0
Requires-Dist: xmltodict
Provides-Extra: credssp
Requires-Dist: requests-credssp>=1.0.0; extra == "credssp"
Provides-Extra: kerberos
Requires-Dist: pykerberos<2.0.0,>=1.2.1; sys_platform != "win32" and extra == "kerberos"
Requires-Dist: winkerberos>=0.5.0; sys_platform == "win32" and extra == "kerberos"
